airflow_reservations/__init__.py
airflow_reservations/config.py
airflow_reservations/policy.py
airflow_reservations-0.1.0.dist-info/licenses/LICENSE
airflow_reservations-0.1.0.dist-info/METADATA
airflow_reservations-0.1.0.dist-info/WHEEL
airflow_reservations-0.1.0.dist-info/entry_points.txt
airflow_reservations-0.1.0.dist-info/top_level.txt
airflow_reservations-0.1.0.dist-info/RECORD
