Metadata-Version: 2.4
Name: airflow-reservations
Version: 0.1.0
Summary: Airflow Cluster Policy for BigQuery reservation management
License: Apache-2.0
Project-URL: Homepage, https://github.com/masthead-data/airflow-reservations
Project-URL: Repository, https://github.com/masthead-data/airflow-reservations
Keywords: airflow,bigquery,reservations,capacity,masthead
Classifier: Development Status :: 4 - Beta
Classifier: Intended Audience :: Developers
Classifier: License :: OSI Approved :: Apache Software License
Classifier: Programming Language :: Python :: 3
Classifier: Programming Language :: Python :: 3.8
Classifier: Programming Language :: Python :: 3.9
Classifier: Programming Language :: Python :: 3.10
Classifier: Programming Language :: Python :: 3.11
Classifier: Programming Language :: Python :: 3.12
Classifier: Framework :: Apache Airflow
Classifier: Topic :: Database
Requires-Python: >=3.8
License-File: LICENSE
Requires-Dist: apache-airflow>=2.6
Provides-Extra: dev
Requires-Dist: pytest>=7.0; extra == "dev"
Requires-Dist: pytest-cov>=4.0; extra == "dev"
Dynamic: license-file
